[
  {
    "name": "article",
    "path": "/article",
    "component": "G:\\\\WORK\\\\Documents\\\\WORK\\\\CloudMD\\\\pages\\\\article.vue",
    "chunkName": "pages/article"
  },
  {
    "name": "login",
    "path": "/login",
    "component": "G:\\\\WORK\\\\Documents\\\\WORK\\\\CloudMD\\\\pages\\\\login.vue",
    "chunkName": "pages/login"
  },
  {
    "name": "search",
    "path": "/search",
    "component": "G:\\\\WORK\\\\Documents\\\\WORK\\\\CloudMD\\\\pages\\\\search.vue",
    "chunkName": "pages/search"
  },
  {
    "name": "user-editor",
    "path": "/user/editor",
    "component": "G:\\\\WORK\\\\Documents\\\\WORK\\\\CloudMD\\\\pages\\\\user\\\\editor.vue",
    "chunkName": "pages/user/editor"
  },
  {
    "name": "index",
    "path": "/",
    "component": "G:\\\\WORK\\\\Documents\\\\WORK\\\\CloudMD\\\\pages\\\\index.vue",
    "chunkName": "pages/index"
  }
]
